fingerscrossed-0.1.1.dist-info/METADATA
fingerscrossed-0.1.1.dist-info/WHEEL
fingerscrossed-0.1.1.dist-info/entry_points.txt
fingerscrossed-0.1.1.dist-info/licenses/LICENSE
fingerscrossed/__init__.py
fingerscrossed/_core.py
fingerscrossed/_stdlib.py
fingerscrossed/_version.py
fingerscrossed/structlog.py
fingerscrossed-0.1.1.dist-info/RECORD
