Metadata-Version: 2.1
Name: fingerscrossed
Version: 0.1.1
Summary: Logging handler wrapper, to buffer the logs and flush them only if something goes wrong
Keywords: logging,structlog
Author: Alexey Shokov
License: MIT
Classifier: Development Status :: 4 - Beta
Classifier: Programming Language :: Python :: 3.10
Classifier: Programming Language :: Python :: 3.11
Classifier: Programming Language :: Python :: 3.12
Classifier: Programming Language :: Python :: 3.13
Classifier: Typing :: Typed
Classifier: Topic :: Software Development
Classifier: Intended Audience :: Developers
Classifier: License :: OSI Approved :: MIT License
Project-URL: homepage, https://github.com/alexeyshockov/fingerscrossed.py
Project-URL: changelog, https://github.com/alexeyshockov/fingerscrossed.py/blob/main/CHANGELOG.md
Requires-Python: >=3.10
